examples/01_basic_usage.py
examples/02_advanced_features.py
examples/03_interactive_notebook.py
examples/04_pdf_report_example.py
examples/05_interactive_notebook.py
examples/06_custom_yaml_rules.py
examples/07_batch_sampling.py
examples/08_data_extraction.py
examples/09_full_system_simulation.py
examples/10_debug_details.py
examples/11_verify_new_features.py
examples/12_test_all_formats.py
examples/13_pdf_export_demo.py
examples/14_professional_pdf_report.py
examples/__init__.py
pydataquality/__init__.py
pydataquality/__main__.py
pydataquality/analyzer.py
pydataquality/cli.py
pydataquality/comparator.py
pydataquality/config.py
pydataquality/reporter.py
pydataquality/utils.py
pydataquality/visualizer.py
pydataquality-0.1.0.dist-info/licenses/LICENSE
tests/__init__.py
tests/test_ai_prompt.py
tests/test_config.py
tests/test_interactive_mock.py
tests/test_pydataquality.py
pydataquality-0.1.0.dist-info/METADATA
pydataquality-0.1.0.dist-info/WHEEL
pydataquality-0.1.0.dist-info/top_level.txt
pydataquality-0.1.0.dist-info/RECORD
