Metadata-Version: 2.4
Name: pydataquality
Version: 0.1.0
Summary: A comprehensive data quality analysis library for pandas DataFrames
Home-page: https://github.com/DominionAkinrotimi/pydataquality
Author: Dominion Akinrotimi
Author-email: Dominion Akinrotimi <contact.dominionakinrotimi@gmail.com>
License: MIT License
Project-URL: Homepage, https://github.com/DominionAkinrotimi/pydataquality
Project-URL: Bug-Tracker, https://github.com/DominionAkinrotimi/pydataquality/issues
Project-URL: Source, https://github.com/DominionAkinrotimi/pydataquality
Classifier: Development Status :: 4 - Beta
Classifier: Intended Audience :: Developers
Classifier: Intended Audience :: Science/Research
Classifier: Topic :: Scientific/Engineering :: Information Analysis
Classifier: License :: OSI Approved :: MIT License
Classifier: Programming Language :: Python :: 3
Classifier: Programming Language :: Python :: 3.7
Classifier: Programming Language :: Python :: 3.8
Classifier: Programming Language :: Python :: 3.9
Classifier: Programming Language :: Python :: 3.10
Classifier: Programming Language :: Python :: 3.11
Classifier: Operating System :: OS Independent
Requires-Python: >=3.7
License-File: LICENSE
Requires-Dist: pandas>=1.3.0
Requires-Dist: numpy>=1.20.0
Requires-Dist: matplotlib>=3.4.0
Requires-Dist: seaborn>=0.11.2
Requires-Dist: jinja2>=3.0.0
Requires-Dist: PyYAML>=5.4
Provides-Extra: dev
Requires-Dist: pytest>=6.0; extra == "dev"
Requires-Dist: pytest-cov>=2.0; extra == "dev"
Requires-Dist: black>=21.0; extra == "dev"
Requires-Dist: flake8>=3.9; extra == "dev"
Provides-Extra: docs
Requires-Dist: sphinx>=4.0; extra == "docs"
Requires-Dist: sphinx-rtd-theme>=1.0; extra == "docs"
Provides-Extra: notebook
Requires-Dist: ipython>=7.0; extra == "notebook"
Requires-Dist: jupyter>=1.0; extra == "notebook"
Dynamic: author
Dynamic: home-page
Dynamic: license-file
Dynamic: requires-python
